climenu.py
climenu-1.8.0.dist-info/DESCRIPTION.rst
climenu-1.8.0.dist-info/METADATA
climenu-1.8.0.dist-info/RECORD
climenu-1.8.0.dist-info/WHEEL
climenu-1.8.0.dist-info/metadata.json
climenu-1.8.0.dist-info/top_level.txt
climenu-1.8.0.dist-info/zip-safe
