Metadata-Version: 2.0
Name: climenu
Version: 1.8.0
Summary: Command-line menu system
Home-page: https://github.com/mtik00/pyclimenu
Author: Timothy McFadden
Author-email: tim@timandjamie.com
License: MIT
Download-URL: https://github.com/mtik00/pyclimenu/releases/download/v1.8.0/climenu-1.8.0.tar.gz
Keywords: cli command-line menu
Platform: UNKNOWN
Classifier: Environment :: Console
Classifier: Intended Audience :: Developers
Classifier: License :: OSI Approved :: MIT License
Classifier: Operating System :: Microsoft :: Windows
Classifier: Operating System :: POSIX :: Linux
Classifier: Programming Language :: Python :: 2
Classifier: Programming Language :: Python :: 2.6
Classifier: Programming Language :: Python :: 2.7
Classifier: Programming Language :: Python :: 3
Classifier: Programming Language :: Python :: 3.3
Classifier: Programming Language :: Python :: 3.4
Classifier: Programming Language :: Python :: 3.5
Classifier: Programming Language :: Python :: 3.6
Classifier: Development Status :: 5 - Production/Stable
